<?xml version="1.0" encoding="UTF-8"?>
<!DOCTYPE mapper PUBLIC "-//mybatis.org//DTD Mapper 3.0//EN" "http://mybatis.org/dtd/mybatis-3-mapper.dtd">
<mapper namespace="com.market.common.mapper.ex.UserBasicBeanMapperEx">
  <resultMap id="BaseResultMap" type="com.market.common.entity.UserBasicBean">
    <!--
      WARNING - @mbg.generated
      This element is automatically generated by MyBatis Generator, do not modify.
    -->
    <id column="id" jdbcType="BIGINT" property="id" />
    <result column="name" jdbcType="VARCHAR" property="name" />
    <result column="sex" jdbcType="INTEGER" property="sex" />
    <result column="cellphone" jdbcType="INTEGER" property="cellphone" />
    <result column="password" jdbcType="VARCHAR" property="password" />
    <result column="status" jdbcType="INTEGER" property="status" />
    <result column="ct" jdbcType="TIMESTAMP" property="ct" />
    <result column="upt" jdbcType="TIMESTAMP" property="upt" />
  </resultMap>
  <sql id="Base_Column_List">
    <!--
      WARNING - @mbg.generated
      This element is automatically generated by MyBatis Generator, do not modify.
    -->
    id, name, sex, cellphone, password, status, ct, upt
  </sql>

</mapper>